[
  {
    "title": "LA CUMBRECITA - ARGENTINA",
    "description": "",
    "photo": "00.webp"
  },
  {
    "title": "LA CUMBRECITA - ARGENTINA",
    "description": "Partiendo a la provincia de Córdoba desde Buenos Aires: 750 km hasta \"Villa General Belgrano\" (600 m) y de allí 40 km, en continuo ascenso, hasta \"La Cumbrecita\" (1500 m).",
    "photo": "01.webp"
  },
  {
    "title": "LA CUMBRECITA - ARGENTINA",
    "description": "A Marina se la ve muy entusiasmada con este viaje. Mientras tanto Manuel, se entretuvo gran parte del trayecto leyendo la historia de \"La Cumbrecita\".",
    "photo": "02.webp"
  },
  {
    "title": "",
    "description": "LA CUMBRECITA - ARGENTINA:",
    "photo": "03.webp"
  },
  {
    "title": "LA CUMBRECITA - ARGENTINA",
    "description": "Puente de Acceso: Cruzando el \"Río del Medio\", se ingresa a la calle principal donde se destacan el \"Centro Cívico\" y las típicas construcciones centroeuropeas en madera.",
    "photo": "04.webp"
  },
  {
    "title": "LA CUMBRECITA - ARGENTINA",
    "description": "Calle Principal: En todo el pueblo abunda la señalética con reminiscencias alpinas tan típicas de Suiza y Austria.",
    "photo": "05.webp"
  },
  {
    "title": "LA CUMBRECITA - ARGENTINA",
    "description": "Marina en la entrada de la \"Municipalidad Local\", edificio compartido con la empresa de teléfonos y una estafeta.",
    "photo": "06.webp"
  },
  {
    "title": "LA CUMBRECITA - ARGENTINA",
    "description": "Como sólo pueden ingresar los autos de quienes se hospedan, nuestro equipaje fue trasladado al hotel mediante los carritos de golf que circulan por todas partes.",
    "photo": "07.webp"
  },
  {
    "title": "LA CUMBRECITA - ARGENTINA",
    "description": "¡Llegamos al hotel! El \"Hotel La Cumbrecita\" es la construcción más antigua y prestigiosa del pueblo. Con el paso de los años, sus dueños, la familia Schefski logró que su hotel se convirtiera en emblema de la localidad, por su tradición y servicio.",
    "photo": "08.webp"
  },
  {
    "title": "LA CUMBRECITA - ARGENTINA",
    "description": "Ya instalada en su habitación, Marina salió para conocer las instalaciones del hotel. IZQ: Puente que comunica el hotel con la piscina. DER: Balcón del tercer piso.",
    "photo": "09.webp"
  },
  {
    "title": "LA CUMBRECITA - ARGENTINA",
    "description": "Parque del hotel: Marina y Manuel conversan con dos huéspedes (madre e hija) que casualmente vivían en Orense (España), donde nació mi madre.",
    "photo": "10.webp"
  },
  {
    "title": "LA CUMBRECITA - ARGENTINA",
    "description": "Por nuestra parte, en busca de dos expresos, Eduardo y yo fuimos a conocer el bar del hotel (DER). Observa el original farol (IZQ) traído de Suiza por los dueños.",
    "photo": "11.webp"
  },
  {
    "title": "LA CUMBRECITA - ARGENTINA",
    "description": "Marina emocionada al reconocer en la recepción del hotel las flores disecadas que ella misma cultivaba en Orense.",
    "photo": "12.webp"
  },
  {
    "title": "LA CUMBRECITA - ARGENTINA",
    "description": "Satisfechos de haber dedicado nuestro primer día de viaje al descanso y a la distracción en las dependencias del hotel. Mañana empiezan los paseos y excursiones...",
    "photo": "13.webp"
  },
  {
    "title": "",
    "description": "LA CUMBRECITA - ARGENTINA:",
    "photo": "14.webp"
  },
  {
    "title": "",
    "description": "LA CUMBRECITA - ARGENTINA",
    "photo": "15.webp"
  },
  {
    "title": "",
    "description": "LA CUMBRECITA - ARGENTINA",
    "photo": "16.webp"
  },
  {
    "title": "",
    "description": "LA CUMBRECITA - ARGENTINA",
    "photo": "17.webp"
  },
  {
    "title": "",
    "description": "LA CUMBRECITA - ARGENTINA",
    "photo": "18.webp"
  },
  {
    "title": "",
    "description": "LA CUMBRECITA - ARGENTINA",
    "photo": "19.webp"
  },
  {
    "title": "",
    "description": "LA CUMBRECITA - ARGENTINA",
    "photo": "20.webp"
  },
  {
    "title": "",
    "description": "LA CUMBRECITA - ARGENTINA",
    "photo": "21.webp"
  },
  {
    "title": "",
    "description": "LA CUMBRECITA - ARGENTINA",
    "photo": "22.webp"
  },
  {
    "title": "",
    "description": "LA CUMBRECITA - ARGENTINA",
    "photo": "23.webp"
  },
  {
    "title": "",
    "description": "LA CUMBRECITA - ARGENTINA",
    "photo": "24.webp"
  },
  {
    "title": "LA CUMBRECITA - ARGENTINA",
    "description": "Disfrutando gaseosas en el \"Bar Suizo\" para atenuar el cansancio de las caminatas.",
    "photo": "25.webp"
  },
  {
    "title": "",
    "description": "LA CUMBRECITA - ARGENTINA:",
    "photo": "26.webp"
  },
  {
    "title": "",
    "description": "LA CUMBRECITA - ARGENTINA",
    "photo": "27.webp"
  },
  {
    "title": "",
    "description": "LA CUMBRECITA - ARGENTINA",
    "photo": "27a.webp"
  },
  {
    "title": "",
    "description": "LA CUMBRECITA - ARGENTINA",
    "photo": "28.webp"
  },
  {
    "title": "",
    "description": "LA CUMBRECITA - ARGENTINA",
    "photo": "29.webp"
  },
  {
    "title": "",
    "description": "LA CUMBRECITA - ARGENTINA",
    "photo": "30-laolla.webp"
  },
  {
    "title": "",
    "description": "LA CUMBRECITA - ARGENTINA",
    "photo": "31-lago-truchas.webp"
  },
  {
    "title": "",
    "description": "LA CUMBRECITA - ARGENTINA",
    "photo": "32.webp"
  },
  {
    "title": "",
    "description": "LA CUMBRECITA - ARGENTINA",
    "photo": "33.webp"
  },
  {
    "title": "",
    "description": "LA CUMBRECITA - ARGENTINA:",
    "photo": "34.webp"
  },
  {
    "title": "",
    "description": "LA CUMBRECITA - ARGENTINA",
    "photo": "35.webp"
  },
  {
    "title": "",
    "description": "LA CUMBRECITA - ARGENTINA",
    "photo": "36.webp"
  },
  {
    "title": "",
    "description": "LA CUMBRECITA - ARGENTINA",
    "photo": "37.webp"
  },
  {
    "title": "",
    "description": "LA CUMBRECITA - ARGENTINA",
    "photo": "38.webp"
  },
  {
    "title": "",
    "description": "LA CUMBRECITA - ARGENTINA",
    "photo": "mirlo1.webp"
  },
  {
    "title": "",
    "description": "LA CUMBRECITA - ARGENTINA",
    "photo": "40.webp"
  },
  {
    "title": "",
    "description": "LA CUMBRECITA - ARGENTINA",
    "photo": "40a.webp"
  },
  {
    "title": "",
    "description": "LA CUMBRECITA - ARGENTINA",
    "photo": "41.webp"
  },
  {
    "title": "",
    "description": "LA CUMBRECITA - ARGENTINA:",
    "photo": "42.webp"
  },
  {
    "title": "",
    "description": "LA CUMBRECITA - ARGENTINA",
    "photo": "43.webp"
  },
  {
    "title": "",
    "description": "LA CUMBRECITA - ARGENTINA",
    "photo": "44-grande.webp"
  },
  {
    "title": "",
    "description": "LA CUMBRECITA - ARGENTINA",
    "photo": "45.webp"
  },
  {
    "title": "",
    "description": "LA CUMBRECITA - ARGENTINA",
    "photo": "46-RemansoNegro.webp"
  },
  {
    "title": "",
    "description": "LA CUMBRECITA - ARGENTINA",
    "photo": "47.webp"
  },
  {
    "title": "",
    "description": "LA CUMBRECITA - ARGENTINA",
    "photo": "48.webp"
  },
  {
    "title": "",
    "description": "LA CUMBRECITA - ARGENTINA",
    "photo": "49.webp"
  },
  {
    "title": "",
    "description": "LA CUMBRECITA - ARGENTINA:",
    "photo": "50.webp"
  },
  {
    "title": "",
    "description": "LA CUMBRECITA - ARGENTINA",
    "photo": "51.webp"
  },
  {
    "title": "",
    "description": "LA CUMBRECITA - ARGENTINA",
    "photo": "52.webp"
  },
  {
    "title": "",
    "description": "LA CUMBRECITA - ARGENTINA",
    "photo": "53.webp"
  },
  {
    "title": "",
    "description": "LA CUMBRECITA - ARGENTINA",
    "photo": "54.webp"
  },
  {
    "title": "",
    "description": "LA CUMBRECITA - ARGENTINA",
    "photo": "55.webp"
  },
  {
    "title": "",
    "description": "LA CUMBRECITA - ARGENTINA",
    "photo": "56.webp"
  },
  {
    "title": "",
    "description": "LA CUMBRECITA - ARGENTINA:",
    "photo": "57.webp"
  },
  {
    "title": "",
    "description": "LA CUMBRECITA - ARGENTINA",
    "photo": "58.webp"
  },
  {
    "title": "",
    "description": "LA CUMBRECITA - ARGENTINA",
    "photo": "59.webp"
  },
  {
    "title": "",
    "description": "LA CUMBRECITA - ARGENTINA",
    "photo": "60.webp"
  },
  {
    "title": "",
    "description": "LA CUMBRECITA - ARGENTINA",
    "photo": "61.webp"
  },
  {
    "title": "",
    "description": "LA CUMBRECITA - ARGENTINA",
    "photo": "62.webp"
  },
  {
    "title": "",
    "description": "LA CUMBRECITA - ARGENTINA:",
    "photo": "63.webp"
  },
  {
    "title": "",
    "description": "LA CUMBRECITA - ARGENTINA",
    "photo": "64.webp"
  },
  {
    "title": "",
    "description": "LA CUMBRECITA - ARGENTINA",
    "photo": "65.webp"
  },
  {
    "title": "",
    "description": "LA CUMBRECITA - ARGENTINA",
    "photo": "66.webp"
  },
  {
    "title": "",
    "description": "LA CUMBRECITA - ARGENTINA",
    "photo": "67.webp"
  },
  {
    "title": "",
    "description": "LA CUMBRECITA - ARGENTINA",
    "photo": "68.webp"
  },
  {
    "title": "",
    "description": "LA CUMBRECITA - ARGENTINA",
    "photo": "69.webp"
  },
  {
    "title": "",
    "description": "LA CUMBRECITA - ARGENTINA",
    "photo": "70.webp"
  },
  {
    "title": "",
    "description": "LA CUMBRECITA - ARGENTINA",
    "photo": "71.webp"
  },
  {
    "title": "",
    "description": "LA CUMBRECITA - ARGENTINA",
    "photo": "72.webp"
  },
  {
    "title": "",
    "description": "LA CUMBRECITA - ARGENTINA",
    "photo": "73.webp"
  },
  {
    "title": "",
    "description": "LA CUMBRECITA - ARGENTINA",
    "photo": "74.webp"
  },
  {
    "title": "",
    "description": "LA CUMBRECITA - ARGENTINA",
    "photo": "75.webp"
  },
  {
    "title": "",
    "description": "LA CUMBRECITA - ARGENTINA",
    "photo": "76.webp"
  },
  {
    "title": "",
    "description": "LA CUMBRECITA - ARGENTINA",
    "photo": "77.webp"
  },
  {
    "title": "",
    "description": "LA CUMBRECITA - ARGENTINA",
    "photo": "78.webp"
  },
  {
    "title": "",
    "description": "LA CUMBRECITA - ARGENTINA",
    "photo": "79.webp"
  },
  {
    "title": "",
    "description": "LA CUMBRECITA - ARGENTINA",
    "photo": "80.webp"
  },
  {
    "title": "",
    "description": "LA CUMBRECITA - ARGENTINA",
    "photo": "81.webp"
  },
  {
    "title": "",
    "description": "LA CUMBRECITA - ARGENTINA",
    "photo": "82.webp"
  }
]